sqlite_backup/__init__.py
sqlite_backup/__main__.py
sqlite_backup/core.py
sqlite_backup/log.py
sqlite_backup/py.typed
sqlite_backup-0.1.8.dist-info/licenses/LICENSE
sqlite_backup-0.1.8.dist-info/METADATA
sqlite_backup-0.1.8.dist-info/WHEEL
sqlite_backup-0.1.8.dist-info/entry_points.txt
sqlite_backup-0.1.8.dist-info/top_level.txt
sqlite_backup-0.1.8.dist-info/RECORD
