Metadata-Version: 2.4
Name: sqlite_backup
Version: 0.1.8
Summary: A tool to copy sqlite databases you don't own
Author: purarue
License-Expression: MIT
Project-URL: Homepage, https://github.com/purarue/sqlite_backup
Keywords: database,sqlite
Classifier: Programming Language :: Python
Classifier: Programming Language :: Python :: 3
Classifier: Programming Language :: Python :: 3.8
Classifier: Programming Language :: Python :: 3.10
Classifier: Programming Language :: Python :: 3.11
Classifier: Programming Language :: Python :: 3.12
Classifier: Programming Language :: Python :: 3.13
Requires-Python: >=3.10
License-File: LICENSE
Requires-Dist: click>=8.0
Requires-Dist: logzero
Provides-Extra: testing
Requires-Dist: pytest; extra == "testing"
Requires-Dist: mypy; extra == "testing"
Requires-Dist: flake8; extra == "testing"
Requires-Dist: pytest-reraise; extra == "testing"
Dynamic: license-file
